DFF/dff.v

// ----------------------------------------------
// DFF POSEDGE ASYNCHRONOUS
// ----------------------------------------------
module dff_Pe_As(q,d,clk,rst);
  input clk,rst,d;
  output reg q;
  
  always@ (posedge clk or posedge rst)
    if(rst)
      q=1'b0;
  	else
      q<=d;
  
endmodule


// ----------------------------------------------
// DFF NEGEDGE ASYNCHRONOUS
// ----------------------------------------------
module dff_Ne_As(q,d,clk,rst);
  input clk,rst,d;
  output reg q;
  
  always@ (negedge clk or posedge rst)
    if(rst)
      q=1'b0;
  	else
      q<=d;
  
endmodule

DFF/dff_tb.v
`timescale 1ns/1ns
`include "dff.v"
// ----------------------------------------------
// DFF POSEDGE ASYNCHRONOUS
// ----------------------------------------------

module dff_Pe_As_tb;
  reg clk,rst,d;
  wire q;
  integer i;
  
  dff_Pe_As dff_Ps_As_1(q,d,clk,rst);
  
  initial begin 
    $dumpfile("dff_Pe_As.vcd");
    $dumpvars(0,dff_Pe_As_tb);
    $monitor("time=%d \t rst=%b \t clk=%b\t d=%b \t q=%b",$time,rst,clk,d,q);
    
    for (i=0;i<8;i++) begin 
      {rst,clk,d}=i;
      #10;
    end

// another method for combination---------------
//  rst = 1; d = 0;  #10;  // Reset active
//     rst = 0;         #10;

//     // ✅ More values for d over time
//     for (i = 0; i < 16; i = i + 1) begin
//       d = i % 2;      // alternate 0/1
//       #10;
//     end
// ----------------------------------------
    $finish;
  end
endmodule

// ----------------------------------------------
// DFF NEGEDGE ASYNCHRONOUS
// ----------------------------------------------
module dff_Ne_As_tb;
  reg clk,rst,d;
  wire q;
  integer i;
  
  dff_Ne_As dff_Ns_As_1(q,d,clk,rst);
  
  initial begin 
    $dumpfile("dff_Ne_As.vcd");
    $dumpvars(0,dff_Ne_As_tb);
    $monitor("time=%d \t rst=%b \t clk=%b\t d=%b \t q=%b",$time,rst,clk,d,q);
    
    for (i=0;i<8;i++) begin 
      {rst,clk,d}=i;
      #10;
    end
    $finish;
  end
endmodule

// ==================================================================

DFF/dff_Pe_As.vcd
$date
	Fri Oct 17 20:43:40 2025
$end
$version
	Icarus Verilog
$end
$timescale
	1ns
$end
$scope module dff_Pe_As_tb $end
$var wire 1 ! q $end
$var reg 1 " clk $end
$var reg 1 # d $end
$var reg 1 $ rst $end
$var integer 32 % i [31:0] $end
$scope module dff_Ps_As_1 $end
$var wire 1 " clk $end
$var wire 1 # d $end
$var wire 1 $ rst $end
$var reg 1 ! q $end
$upscope $end
$upscope $end
$enddefinitions $end
$comment Show the parameter values. $end
$dumpall
$end
#0
$dumpvars
b0 %
0$
0#
0"
x!
$end
#10
1#
b1 %
#20
0!
1"
0#
b10 %
#30
1#
b11 %
#40
1$
0"
0#
b100 %
#50
1#
b101 %
#60
1"
0#
b110 %
#70
1#
b111 %
#80
b1000 %
